pylavcogs_shared/__init__.py
pylavcogs_shared/errors.py
pylavcogs_shared/types.py
pylavcogs_shared/converters/__init__.py
pylavcogs_shared/converters/equalizer.py
pylavcogs_shared/converters/locales/bg-BG.po
pylavcogs_shared/converters/locales/cs-CZ.po
pylavcogs_shared/converters/locales/da-DK.po
pylavcogs_shared/converters/locales/de-DE.po
pylavcogs_shared/converters/locales/el-GR.po
pylavcogs_shared/converters/locales/es-ES.po
pylavcogs_shared/converters/locales/fi-FI.po
pylavcogs_shared/converters/locales/fr-FR.po
pylavcogs_shared/converters/locales/hi-IN.po
pylavcogs_shared/converters/locales/hr-HR.po
pylavcogs_shared/converters/locales/hu-HU.po
pylavcogs_shared/converters/locales/it-IT.po
pylavcogs_shared/converters/locales/ja-JP.po
pylavcogs_shared/converters/locales/ko-KR.po
pylavcogs_shared/converters/locales/lt-LT.po
pylavcogs_shared/converters/locales/nb-NO.po
pylavcogs_shared/converters/locales/nl-NL.po
pylavcogs_shared/converters/locales/no-NO.po
pylavcogs_shared/converters/locales/pl-PL.po
pylavcogs_shared/converters/locales/pt-BR.po
pylavcogs_shared/converters/locales/ro-RO.po
pylavcogs_shared/converters/locales/ru-RU.po
pylavcogs_shared/converters/locales/sv-SE.po
pylavcogs_shared/converters/locales/th-TH.po
pylavcogs_shared/converters/locales/tr-TR.po
pylavcogs_shared/converters/locales/uk-UA.po
pylavcogs_shared/converters/locales/vi-VN.po
pylavcogs_shared/converters/locales/zh-CN.po
pylavcogs_shared/converters/locales/zh-TW.po
pylavcogs_shared/locales/bg-BG.po
pylavcogs_shared/locales/cs-CZ.po
pylavcogs_shared/locales/da-DK.po
pylavcogs_shared/locales/de-DE.po
pylavcogs_shared/locales/el-GR.po
pylavcogs_shared/locales/es-ES.po
pylavcogs_shared/locales/fi-FI.po
pylavcogs_shared/locales/fr-FR.po
pylavcogs_shared/locales/hi-IN.po
pylavcogs_shared/locales/hr-HR.po
pylavcogs_shared/locales/hu-HU.po
pylavcogs_shared/locales/it-IT.po
pylavcogs_shared/locales/ja-JP.po
pylavcogs_shared/locales/ko-KR.po
pylavcogs_shared/locales/lt-LT.po
pylavcogs_shared-0.6.1.5.dist-info/LICENSE
pylavcogs_shared-0.6.1.5.dist-info/METADATA
pylavcogs_shared-0.6.1.5.dist-info/WHEEL
pylavcogs_shared-0.6.1.5.dist-info/top_level.txt
pylavcogs_shared-0.6.1.5.dist-info/RECORD
