Metadata-Version: 2.1
Name: pylavcogs-shared
Version: 0.6.1.5
Summary: A Library with shared utilities for PyLav-Cogs
Home-page: https://github.com/Drapersniper/PyLavCog-Shared
Author: Draper
Author-email: draper@draper.wtf
License: AGPLv3
Classifier: Development Status :: 4 - Beta
Classifier: Intended Audience :: Developers
Classifier: Topic :: Software Development :: Libraries
Classifier: Topic :: Software Development :: Libraries :: Python Modules
Classifier: Topic :: Software Development :: Version Control :: Git
Classifier: Topic :: Utilities
Classifier: Typing :: Typed
Classifier: License :: OSI Approved :: GNU Affero General Public License v3 or later (AGPLv3+)
Classifier: Natural Language :: English
Classifier: Operating System :: MacOS :: MacOS X
Classifier: Operating System :: Microsoft :: Windows
Classifier: Operating System :: POSIX :: Linux
Classifier: Programming Language :: Python :: 3 :: Only
Classifier: Programming Language :: Python :: 3.10
Classifier: Programming Language :: Python :: Implementation :: CPython
Requires-Python: <3.11,>=3.10.0
License-File: LICENSE
Requires-Dist: Py-Lav (>=0.11.0.0<1.0.0)
